pgreshape/__init__.py
pgreshape/__main__.py
pgreshape/main.py
pgreshape-0.0.6.dist-info/entry_points.txt
pgreshape-0.0.6.dist-info/LICENSE
pgreshape-0.0.6.dist-info/WHEEL
pgreshape-0.0.6.dist-info/METADATA
pgreshape-0.0.6.dist-info/RECORD
